setup.py
django_muzo.egg-info/PKG-INFO
django_muzo.egg-info/SOURCES.txt
django_muzo.egg-info/dependency_links.txt
django_muzo.egg-info/not-zip-safe
django_muzo.egg-info/requires.txt
django_muzo.egg-info/top_level.txt
muzo/__init__.py
muzo/admin.py
muzo/forms.py
muzo/models.py
muzo/signals.py
muzo/signature.py
muzo/views.py
muzo/ws.py