Metadata-Version: 1.0
Name: django-muzo
Version: 1.1
Summary: Django GP payment module
Home-page: https://github.com/temnoregg/django-muzo
Author: Petr Chalupny
Author-email: temnoregg@gmail.com
License: UNKNOWN
Platform: UNKNOWN
